gender_guesser/__init__.py
gender_guesser/detector.py
gender_guesser/data/nam_dict.txt
gender_guesser-0.3.0.dist-info/DESCRIPTION.rst
gender_guesser-0.3.0.dist-info/METADATA
gender_guesser-0.3.0.dist-info/RECORD
gender_guesser-0.3.0.dist-info/WHEEL
gender_guesser-0.3.0.dist-info/metadata.json
gender_guesser-0.3.0.dist-info/top_level.txt
