Metadata-Version: 2.0
Name: gender-guesser
Version: 0.3.0
Summary: Get the gender from first name.
Home-page: https://github.com/lead-ratings/gender-guesser
Author: Israel Saeta Pérez
Author-email: israel@lead-ratings.com
License: GPLv3
Platform: UNKNOWN
